{
  "event": [
    {
      "listen": "prerequest",
      "script": {
        "exec": [""],
        "packages": {},
        "type": "text/javascript"
      }
    },
    {
      "listen": "test",
      "script": {
        "exec": [""],
        "packages": {},
        "type": "text/javascript"
      }
    }
  ],
  "info": {
    "_exporter_id": "33192992",
    "_postman_id": "6f47d89a-9e13-48c1-b58d-76b6032b6416",
    "name": "Zero Company",
    "schema": "https://schema.getpostman.com/json/collection/v2.1.0/collection.json"
  },
  "item": [
    {
      "item": [
        {
          "name": "Get all",
          "request": {
            "auth": {
              "type": "noauth"
            },
            "header": [],
            "method": "GET",
            "url": {
              "host": ["{{apiUrl}}categories"],
              "raw": "{{apiUrl}}categories"
            }
          },
          "response": []
        },
        {
          "name": "Get all / pagination",
          "request": {
            "auth": {
              "type": "noauth"
            },
            "header": [],
            "method": "GET",
            "url": {
              "host": ["{{apiUrl}}categories"],
              "query": [
                {
                  "key": "offset",
                  "value": "1"
                },
                {
                  "key": "limit",
                  "value": "2"
                }
              ],
              "raw": "{{apiUrl}}categories?offset=1&limit=2"
            }
          },
          "response": []
        },
        {
          "event": [
            {
              "listen": "test",
              "script": {
                "exec": [
                  "var { _id } = JSON.parse(responseBody);\r",
                  "if (_id) postman.setEnvironmentVariable(\"lastCategoryId\", _id);"
                ],
                "packages": {},
                "type": "text/javascript"
              }
            }
          ],
          "name": "Add one",
          "request": {
            "auth": {
              "jwt": [
                {
                  "key": "payload",
                  "type": "string",
                  "value": "{\r\n    \"email\": \"{{jwtAdminEmail}}\"\r\n}\r\n"
                },
                {
                  "key": "addTokenTo",
                  "type": "string",
                  "value": "header"
                },
                {
                  "key": "header",
                  "type": "string",
                  "value": ""
                },
                {
                  "key": "secret",
                  "type": "string",
                  "value": "{{jwtSecret}}"
                },
                {
                  "key": "algorithm",
                  "type": "string",
                  "value": "HS256"
                },
                {
                  "key": "isSecretBase64Encoded",
                  "type": "boolean",
                  "value": false
                },
                {
                  "key": "headerPrefix",
                  "type": "string",
                  "value": "Bearer"
                },
                {
                  "key": "queryParamKey",
                  "type": "string",
                  "value": "token"
                }
              ],
              "type": "jwt"
            },
            "body": {
              "mode": "raw",
              "options": {
                "raw": {
                  "language": "json"
                }
              },
              "raw": "{\r\n    \"description\": \"Some description\",\r\n    \"name\": \"HiTech\",\r\n    \"tagline\": \"Some tagline\"\r\n}"
            },
            "header": [],
            "method": "POST",
            "url": {
              "host": ["{{apiUrl}}categories"],
              "raw": "{{apiUrl}}categories"
            }
          },
          "response": []
        },
        {
          "name": "Get one",
          "request": {
            "auth": {
              "type": "noauth"
            },
            "header": [],
            "method": "GET",
            "url": {
              "host": ["{{apiUrl}}categories"],
              "path": ["{{lastCategoryId}}"],
              "raw": "{{apiUrl}}categories/{{lastCategoryId}}"
            }
          },
          "response": []
        },
        {
          "event": [
            {
              "listen": "test",
              "script": {
                "exec": [""],
                "packages": {},
                "type": "text/javascript"
              }
            }
          ],
          "name": "Update one",
          "request": {
            "auth": {
              "jwt": [
                {
                  "key": "payload",
                  "type": "string",
                  "value": "{\r\n    \"email\": \"{{jwtAdminEmail}}\"\r\n}\r\n"
                },
                {
                  "key": "addTokenTo",
                  "type": "string",
                  "value": "header"
                },
                {
                  "key": "secret",
                  "type": "string",
                  "value": "{{jwtSecret}}"
                },
                {
                  "key": "algorithm",
                  "type": "string",
                  "value": "HS256"
                },
                {
                  "key": "isSecretBase64Encoded",
                  "type": "boolean",
                  "value": false
                },
                {
                  "key": "headerPrefix",
                  "type": "string",
                  "value": "Bearer"
                },
                {
                  "key": "queryParamKey",
                  "type": "string",
                  "value": "token"
                },
                {
                  "key": "header",
                  "type": "string",
                  "value": "{}"
                }
              ],
              "type": "jwt"
            },
            "body": {
              "mode": "raw",
              "options": {
                "raw": {
                  "language": "json"
                }
              },
              "raw": "{\r\n    \"description\": \"Some description 2\",\r\n    \"tagline\": \"Some tagline 2\"\r\n}"
            },
            "header": [],
            "method": "PUT",
            "url": {
              "host": ["{{apiUrl}}categories"],
              "path": ["{{lastCategoryId}}"],
              "raw": "{{apiUrl}}categories/{{lastCategoryId}}"
            }
          },
          "response": []
        },
        {
          "name": "Delete one",
          "request": {
            "auth": {
              "jwt": [
                {
                  "key": "payload",
                  "type": "string",
                  "value": "{\r\n    \"email\": \"{{jwtAdminEmail}}\"\r\n}\r\n"
                },
                {
                  "key": "secret",
                  "type": "string",
                  "value": "{{jwtSecret}}"
                },
                {
                  "key": "addTokenTo",
                  "type": "string",
                  "value": "header"
                },
                {
                  "key": "algorithm",
                  "type": "string",
                  "value": "HS256"
                },
                {
                  "key": "isSecretBase64Encoded",
                  "type": "boolean",
                  "value": false
                },
                {
                  "key": "headerPrefix",
                  "type": "string",
                  "value": "Bearer"
                },
                {
                  "key": "queryParamKey",
                  "type": "string",
                  "value": "token"
                },
                {
                  "key": "header",
                  "type": "string",
                  "value": "{}"
                }
              ],
              "type": "jwt"
            },
            "header": [],
            "method": "DELETE",
            "url": {
              "host": ["{{apiUrl}}categories"],
              "path": ["{{lastCategoryId}}"],
              "raw": "{{apiUrl}}categories/{{lastCategoryId}}"
            }
          },
          "response": []
        },
        {
          "name": "Get companies",
          "request": {
            "auth": {
              "type": "noauth"
            },
            "header": [],
            "method": "GET",
            "url": {
              "host": ["{{apiUrl}}categories"],
              "path": ["{{lastCategoryId}}", "companies"],
              "raw": "{{apiUrl}}categories/{{lastCategoryId}}/companies"
            }
          },
          "response": []
        },
        {
          "name": "Get companies / pagination",
          "request": {
            "auth": {
              "type": "noauth"
            },
            "header": [],
            "method": "GET",
            "url": {
              "host": ["{{apiUrl}}categories"],
              "path": ["{{lastCategoryId}}", "companies"],
              "query": [
                {
                  "key": "offset",
                  "value": "1"
                },
                {
                  "key": "limit",
                  "value": "2"
                }
              ],
              "raw": "{{apiUrl}}categories/{{lastCategoryId}}/companies?offset=1&limit=2"
            }
          },
          "response": []
        }
      ],
      "name": "Categories"
    },
    {
      "item": [
        {
          "name": "Get all",
          "request": {
            "auth": {
              "type": "noauth"
            },
            "header": [],
            "method": "GET",
            "url": {
              "host": ["{{apiUrl}}companies"],
              "raw": "{{apiUrl}}companies"
            }
          },
          "response": []
        },
        {
          "name": "Get all / pagination",
          "request": {
            "auth": {
              "type": "noauth"
            },
            "header": [],
            "method": "GET",
            "url": {
              "host": ["{{apiUrl}}companies"],
              "query": [
                {
                  "key": "offset",
                  "value": "1"
                },
                {
                  "key": "limit",
                  "value": "2"
                }
              ],
              "raw": "{{apiUrl}}companies?offset=1&limit=2"
            }
          },
          "response": []
        },
        {
          "event": [
            {
              "listen": "test",
              "script": {
                "exec": [
                  "var { _id } = JSON.parse(responseBody);\r",
                  "if (_id) postman.setEnvironmentVariable(\"lastCompanyId\", _id);"
                ],
                "packages": {},
                "type": "text/javascript"
              }
            }
          ],
          "name": "Add one",
          "request": {
            "auth": {
              "jwt": [
                {
                  "key": "payload",
                  "type": "string",
                  "value": "{\r\n    \"email\": \"{{jwtEmail}}\"\r\n}\r\n"
                },
                {
                  "key": "secret",
                  "type": "string",
                  "value": "{{jwtSecret}}"
                },
                {
                  "key": "addTokenTo",
                  "type": "string",
                  "value": "header"
                },
                {
                  "key": "algorithm",
                  "type": "string",
                  "value": "HS256"
                },
                {
                  "key": "isSecretBase64Encoded",
                  "type": "boolean",
                  "value": false
                },
                {
                  "key": "headerPrefix",
                  "type": "string",
                  "value": "Bearer"
                },
                {
                  "key": "queryParamKey",
                  "type": "string",
                  "value": "token"
                },
                {
                  "key": "header",
                  "type": "string",
                  "value": "{}"
                }
              ],
              "type": "jwt"
            },
            "body": {
              "formdata": [
                {
                  "key": "categories[]",
                  "type": "text",
                  "value": "{{lastCategoryId}}"
                },
                {
                  "key": "description",
                  "type": "text",
                  "value": "Some description"
                },
                {
                  "key": "founders[0].email",
                  "type": "text",
                  "value": "{{jwtEmail}}"
                },
                {
                  "key": "founders[0].share",
                  "type": "text",
                  "value": "10000"
                },
                {
                  "key": "images",
                  "src": [
                    "zero-company/company/images1.webp",
                    "zero-company/company/images2.jpg"
                  ],
                  "type": "file"
                },
                {
                  "key": "name",
                  "type": "text",
                  "value": "Travel aggregator"
                },
                {
                  "key": "logo",
                  "src": "zero-company/company/logo1.jpg",
                  "type": "file"
                },
                {
                  "key": "targetValue",
                  "type": "text",
                  "value": "100000"
                },
                {
                  "key": "website",
                  "type": "text",
                  "value": "http://cats.com/"
                }
              ],
              "mode": "formdata"
            },
            "header": [],
            "method": "POST",
            "url": {
              "host": ["{{apiUrl}}companies"],
              "raw": "{{apiUrl}}companies"
            }
          },
          "response": []
        },
        {
          "name": "Get one",
          "request": {
            "auth": {
              "type": "noauth"
            },
            "header": [],
            "method": "GET",
            "url": {
              "host": ["{{apiUrl}}companies"],
              "path": ["{{lastCompanyId}}"],
              "raw": "{{apiUrl}}companies/{{lastCompanyId}}"
            }
          },
          "response": []
        },
        {
          "event": [
            {
              "listen": "test",
              "script": {
                "exec": [""],
                "packages": {},
                "type": "text/javascript"
              }
            }
          ],
          "name": "Update one",
          "request": {
            "auth": {
              "jwt": [
                {
                  "key": "payload",
                  "type": "string",
                  "value": "{\r\n    \"email\": \"{{jwtAdminEmail}}\"\r\n}\r\n"
                },
                {
                  "key": "secret",
                  "type": "string",
                  "value": "{{jwtSecret}}"
                },
                {
                  "key": "addTokenTo",
                  "type": "string",
                  "value": "header"
                },
                {
                  "key": "algorithm",
                  "type": "string",
                  "value": "HS256"
                },
                {
                  "key": "isSecretBase64Encoded",
                  "type": "boolean",
                  "value": false
                },
                {
                  "key": "headerPrefix",
                  "type": "string",
                  "value": "Bearer"
                },
                {
                  "key": "queryParamKey",
                  "type": "string",
                  "value": "token"
                },
                {
                  "key": "header",
                  "type": "string",
                  "value": "{}"
                }
              ],
              "type": "jwt"
            },
            "body": {
              "formdata": [
                {
                  "key": "name",
                  "type": "text",
                  "value": "Travel aggregator 2"
                },
                {
                  "key": "logo",
                  "src": "zero-company/company/logo2.webp",
                  "type": "file"
                },
                {
                  "key": "website",
                  "type": "text",
                  "value": ""
                }
              ],
              "mode": "formdata"
            },
            "header": [],
            "method": "PUT",
            "url": {
              "host": ["{{apiUrl}}companies"],
              "path": ["{{lastCompanyId}}"],
              "raw": "{{apiUrl}}companies/{{lastCompanyId}}"
            }
          },
          "response": []
        },
        {
          "name": "Delete one",
          "request": {
            "auth": {
              "jwt": [
                {
                  "key": "payload",
                  "type": "string",
                  "value": "{\r\n    \"email\": \"{{jwtAdminEmail}}\"\r\n}\r\n"
                },
                {
                  "key": "secret",
                  "type": "string",
                  "value": "{{jwtSecret}}"
                },
                {
                  "key": "addTokenTo",
                  "type": "string",
                  "value": "header"
                },
                {
                  "key": "algorithm",
                  "type": "string",
                  "value": "HS256"
                },
                {
                  "key": "isSecretBase64Encoded",
                  "type": "boolean",
                  "value": false
                },
                {
                  "key": "headerPrefix",
                  "type": "string",
                  "value": "Bearer"
                },
                {
                  "key": "queryParamKey",
                  "type": "string",
                  "value": "token"
                },
                {
                  "key": "header",
                  "type": "string",
                  "value": "{}"
                }
              ],
              "type": "jwt"
            },
            "header": [],
            "method": "DELETE",
            "url": {
              "host": ["{{apiUrl}}companies"],
              "path": ["{{lastCompanyId}}"],
              "raw": "{{apiUrl}}companies/{{lastCompanyId}}"
            }
          },
          "response": []
        }
      ],
      "name": "Companies"
    },
    {
      "item": [
        {
          "event": [
            {
              "listen": "test",
              "script": {
                "exec": [""],
                "packages": {},
                "type": "text/javascript"
              }
            }
          ],
          "name": "Add one",
          "request": {
            "auth": {
              "jwt": [
                {
                  "key": "payload",
                  "type": "string",
                  "value": "{\r\n    \"email\": \"{{jwtEmail}}\"\r\n}\r\n"
                },
                {
                  "key": "secret",
                  "type": "string",
                  "value": "{{jwtSecret}}"
                },
                {
                  "key": "addTokenTo",
                  "type": "string",
                  "value": "header"
                },
                {
                  "key": "algorithm",
                  "type": "string",
                  "value": "HS256"
                },
                {
                  "key": "isSecretBase64Encoded",
                  "type": "boolean",
                  "value": false
                },
                {
                  "key": "headerPrefix",
                  "type": "string",
                  "value": "Bearer"
                },
                {
                  "key": "queryParamKey",
                  "type": "string",
                  "value": "token"
                },
                {
                  "key": "header",
                  "type": "string",
                  "value": "{}"
                }
              ],
              "type": "jwt"
            },
            "body": {
              "mode": "raw",
              "options": {
                "raw": {
                  "language": "json"
                }
              },
              "raw": "{\r\n    \"email\": \"{{jwtEmail}}\",\r\n    \"firstName\": \"John\",\r\n    \"lastName\": \"Smith\"\r\n}"
            },
            "header": [],
            "method": "POST",
            "url": {
              "host": ["{{apiUrl}}me"],
              "raw": "{{apiUrl}}me"
            }
          },
          "response": []
        },
        {
          "name": "Get one",
          "request": {
            "auth": {
              "jwt": [
                {
                  "key": "payload",
                  "type": "string",
                  "value": "{\r\n    \"email\": \"{{jwtEmail}}\"\r\n}\r\n"
                },
                {
                  "key": "secret",
                  "type": "string",
                  "value": "{{jwtSecret}}"
                },
                {
                  "key": "addTokenTo",
                  "type": "string",
                  "value": "header"
                },
                {
                  "key": "algorithm",
                  "type": "string",
                  "value": "HS256"
                },
                {
                  "key": "isSecretBase64Encoded",
                  "type": "boolean",
                  "value": false
                },
                {
                  "key": "headerPrefix",
                  "type": "string",
                  "value": "Bearer"
                },
                {
                  "key": "queryParamKey",
                  "type": "string",
                  "value": "token"
                },
                {
                  "key": "header",
                  "type": "string",
                  "value": "{}"
                }
              ],
              "type": "jwt"
            },
            "header": [],
            "method": "GET",
            "url": {
              "host": ["{{apiUrl}}me"],
              "raw": "{{apiUrl}}me"
            }
          },
          "response": []
        },
        {
          "name": "Update one",
          "request": {
            "auth": {
              "jwt": [
                {
                  "key": "payload",
                  "type": "string",
                  "value": "{\r\n    \"email\": \"{{jwtEmail}}\"\r\n}\r\n"
                },
                {
                  "key": "secret",
                  "type": "string",
                  "value": "{{jwtSecret}}"
                },
                {
                  "key": "addTokenTo",
                  "type": "string",
                  "value": "header"
                },
                {
                  "key": "algorithm",
                  "type": "string",
                  "value": "HS256"
                },
                {
                  "key": "isSecretBase64Encoded",
                  "type": "boolean",
                  "value": false
                },
                {
                  "key": "headerPrefix",
                  "type": "string",
                  "value": "Bearer"
                },
                {
                  "key": "queryParamKey",
                  "type": "string",
                  "value": "token"
                },
                {
                  "key": "header",
                  "type": "string",
                  "value": "{}"
                }
              ],
              "type": "jwt"
            },
            "body": {
              "mode": "raw",
              "options": {
                "raw": {
                  "language": "json"
                }
              },
              "raw": "{\r\n    \"firstName\": \"John 2\",\r\n    \"lastName\": \"Smith 2\"\r\n}"
            },
            "header": [],
            "method": "PUT",
            "url": {
              "host": ["{{apiUrl}}me"],
              "raw": "{{apiUrl}}me"
            }
          },
          "response": []
        },
        {
          "name": "Delete one",
          "request": {
            "auth": {
              "jwt": [
                {
                  "key": "payload",
                  "type": "string",
                  "value": "{\r\n    \"email\": \"{{jwtEmail}}\"\r\n}\r\n\r\n"
                },
                {
                  "key": "secret",
                  "type": "string",
                  "value": "{{jwtSecret}}"
                },
                {
                  "key": "addTokenTo",
                  "type": "string",
                  "value": "header"
                },
                {
                  "key": "algorithm",
                  "type": "string",
                  "value": "HS256"
                },
                {
                  "key": "isSecretBase64Encoded",
                  "type": "boolean",
                  "value": false
                },
                {
                  "key": "headerPrefix",
                  "type": "string",
                  "value": "Bearer"
                },
                {
                  "key": "queryParamKey",
                  "type": "string",
                  "value": "token"
                },
                {
                  "key": "header",
                  "type": "string",
                  "value": "{}"
                }
              ],
              "type": "jwt"
            },
            "header": [],
            "method": "DELETE",
            "url": {
              "host": ["{{apiUrl}}me"],
              "raw": "{{apiUrl}}me"
            }
          },
          "response": []
        },
        {
          "name": "Get companies",
          "request": {
            "auth": {
              "jwt": [
                {
                  "key": "payload",
                  "type": "string",
                  "value": "{\r\n    \"email\": \"{{jwtEmail}}\"\r\n}\r\n"
                },
                {
                  "key": "secret",
                  "type": "string",
                  "value": "{{jwtSecret}}"
                },
                {
                  "key": "addTokenTo",
                  "type": "string",
                  "value": "header"
                },
                {
                  "key": "algorithm",
                  "type": "string",
                  "value": "HS256"
                },
                {
                  "key": "isSecretBase64Encoded",
                  "type": "boolean",
                  "value": false
                },
                {
                  "key": "headerPrefix",
                  "type": "string",
                  "value": "Bearer"
                },
                {
                  "key": "queryParamKey",
                  "type": "string",
                  "value": "token"
                },
                {
                  "key": "header",
                  "type": "string",
                  "value": "{}"
                }
              ],
              "type": "jwt"
            },
            "header": [],
            "method": "GET",
            "url": {
              "host": ["{{apiUrl}}me"],
              "path": ["companies"],
              "raw": "{{apiUrl}}me/companies"
            }
          },
          "response": []
        },
        {
          "name": "Get companies / pagination",
          "request": {
            "auth": {
              "jwt": [
                {
                  "key": "payload",
                  "type": "string",
                  "value": "{\r\n    \"email\": \"{{jwtEmail}}\"\r\n}\r\n"
                },
                {
                  "key": "secret",
                  "type": "string",
                  "value": "{{jwtSecret}}"
                },
                {
                  "key": "addTokenTo",
                  "type": "string",
                  "value": "header"
                },
                {
                  "key": "algorithm",
                  "type": "string",
                  "value": "HS256"
                },
                {
                  "key": "isSecretBase64Encoded",
                  "type": "boolean",
                  "value": false
                },
                {
                  "key": "headerPrefix",
                  "type": "string",
                  "value": "Bearer"
                },
                {
                  "key": "queryParamKey",
                  "type": "string",
                  "value": "token"
                },
                {
                  "key": "header",
                  "type": "string",
                  "value": "{}"
                }
              ],
              "type": "jwt"
            },
            "header": [],
            "method": "GET",
            "url": {
              "host": ["{{apiUrl}}me"],
              "path": ["companies"],
              "query": [
                {
                  "key": "offset",
                  "value": "1"
                },
                {
                  "key": "limit",
                  "value": "2"
                }
              ],
              "raw": "{{apiUrl}}me/companies?offset=1&limit=2"
            }
          },
          "response": []
        }
      ],
      "name": "Me"
    },
    {
      "item": [
        {
          "name": "Get all",
          "request": {
            "auth": {
              "jwt": [
                {
                  "key": "payload",
                  "type": "string",
                  "value": "{\r\n    \"email\": \"{{jwtEmail}}\"\r\n}\r\n"
                },
                {
                  "key": "secret",
                  "type": "string",
                  "value": "{{jwtSecret}}"
                },
                {
                  "key": "addTokenTo",
                  "type": "string",
                  "value": "header"
                },
                {
                  "key": "algorithm",
                  "type": "string",
                  "value": "HS256"
                },
                {
                  "key": "isSecretBase64Encoded",
                  "type": "boolean",
                  "value": false
                },
                {
                  "key": "headerPrefix",
                  "type": "string",
                  "value": "Bearer"
                },
                {
                  "key": "queryParamKey",
                  "type": "string",
                  "value": "token"
                },
                {
                  "key": "header",
                  "type": "string",
                  "value": "{}"
                }
              ],
              "type": "jwt"
            },
            "header": [],
            "method": "GET",
            "url": {
              "host": ["{{apiUrl}}users"],
              "raw": "{{apiUrl}}users"
            }
          },
          "response": []
        },
        {
          "name": "Get all / pagination",
          "request": {
            "auth": {
              "jwt": [
                {
                  "key": "payload",
                  "type": "string",
                  "value": "{\r\n    \"email\": \"{{jwtEmail}}\"\r\n}\r\n"
                },
                {
                  "key": "secret",
                  "type": "string",
                  "value": "{{jwtSecret}}"
                },
                {
                  "key": "addTokenTo",
                  "type": "string",
                  "value": "header"
                },
                {
                  "key": "algorithm",
                  "type": "string",
                  "value": "HS256"
                },
                {
                  "key": "isSecretBase64Encoded",
                  "type": "boolean",
                  "value": false
                },
                {
                  "key": "headerPrefix",
                  "type": "string",
                  "value": "Bearer"
                },
                {
                  "key": "queryParamKey",
                  "type": "string",
                  "value": "token"
                },
                {
                  "key": "header",
                  "type": "string",
                  "value": "{}"
                }
              ],
              "type": "jwt"
            },
            "header": [],
            "method": "GET",
            "url": {
              "host": ["{{apiUrl}}users"],
              "query": [
                {
                  "key": "offset",
                  "value": "1"
                },
                {
                  "key": "limit",
                  "value": "2"
                }
              ],
              "raw": "{{apiUrl}}users?offset=1&limit=2"
            }
          },
          "response": []
        },
        {
          "event": [
            {
              "listen": "test",
              "script": {
                "exec": [""],
                "packages": {},
                "type": "text/javascript"
              }
            }
          ],
          "name": "Add one",
          "request": {
            "auth": {
              "jwt": [
                {
                  "key": "payload",
                  "type": "string",
                  "value": "{\r\n    \"email\": \"{{jwtAdminEmail}}\"\r\n}\r\n"
                },
                {
                  "key": "secret",
                  "type": "string",
                  "value": "{{jwtSecret}}"
                },
                {
                  "key": "addTokenTo",
                  "type": "string",
                  "value": "header"
                },
                {
                  "key": "algorithm",
                  "type": "string",
                  "value": "HS256"
                },
                {
                  "key": "isSecretBase64Encoded",
                  "type": "boolean",
                  "value": false
                },
                {
                  "key": "headerPrefix",
                  "type": "string",
                  "value": "Bearer"
                },
                {
                  "key": "queryParamKey",
                  "type": "string",
                  "value": "token"
                },
                {
                  "key": "header",
                  "type": "string",
                  "value": "{}"
                }
              ],
              "type": "jwt"
            },
            "body": {
              "mode": "raw",
              "options": {
                "raw": {
                  "language": "json"
                }
              },
              "raw": "{\r\n    \"email\": \"{{jwtEmail}}\",\r\n    \"firstName\": \"John\",\r\n    \"lastName\": \"Smith\"\r\n}"
            },
            "header": [],
            "method": "POST",
            "url": {
              "host": ["{{apiUrl}}users"],
              "raw": "{{apiUrl}}users"
            }
          },
          "response": []
        },
        {
          "name": "Get one",
          "request": {
            "auth": {
              "jwt": [
                {
                  "key": "payload",
                  "type": "string",
                  "value": "{\r\n    \"email\": \"{{jwtEmail}}\"\r\n}\r\n"
                },
                {
                  "key": "secret",
                  "type": "string",
                  "value": "{{jwtSecret}}"
                },
                {
                  "key": "addTokenTo",
                  "type": "string",
                  "value": "header"
                },
                {
                  "key": "algorithm",
                  "type": "string",
                  "value": "HS256"
                },
                {
                  "key": "isSecretBase64Encoded",
                  "type": "boolean",
                  "value": false
                },
                {
                  "key": "headerPrefix",
                  "type": "string",
                  "value": "Bearer"
                },
                {
                  "key": "queryParamKey",
                  "type": "string",
                  "value": "token"
                },
                {
                  "key": "header",
                  "type": "string",
                  "value": "{}"
                }
              ],
              "type": "jwt"
            },
            "header": [],
            "method": "GET",
            "url": {
              "host": ["{{apiUrl}}users"],
              "path": ["{{jwtEmail}}"],
              "raw": "{{apiUrl}}users/{{jwtEmail}}"
            }
          },
          "response": []
        },
        {
          "name": "Update one",
          "request": {
            "auth": {
              "jwt": [
                {
                  "key": "payload",
                  "type": "string",
                  "value": "{\r\n    \"email\": \"{{jwtAdminEmail}}\"\r\n}\r\n"
                },
                {
                  "key": "secret",
                  "type": "string",
                  "value": "{{jwtSecret}}"
                },
                {
                  "key": "addTokenTo",
                  "type": "string",
                  "value": "header"
                },
                {
                  "key": "algorithm",
                  "type": "string",
                  "value": "HS256"
                },
                {
                  "key": "isSecretBase64Encoded",
                  "type": "boolean",
                  "value": false
                },
                {
                  "key": "headerPrefix",
                  "type": "string",
                  "value": "Bearer"
                },
                {
                  "key": "queryParamKey",
                  "type": "string",
                  "value": "token"
                },
                {
                  "key": "header",
                  "type": "string",
                  "value": "{}"
                }
              ],
              "type": "jwt"
            },
            "body": {
              "mode": "raw",
              "options": {
                "raw": {
                  "language": "json"
                }
              },
              "raw": "{\r\n    \"firstName\": \"John 2\",\r\n    \"lastName\": \"Smith 2\"\r\n}"
            },
            "header": [],
            "method": "PUT",
            "url": {
              "host": ["{{apiUrl}}users"],
              "path": ["{{jwtEmail}}"],
              "raw": "{{apiUrl}}users/{{jwtEmail}}"
            }
          },
          "response": []
        },
        {
          "name": "Delete one",
          "request": {
            "auth": {
              "jwt": [
                {
                  "key": "payload",
                  "type": "string",
                  "value": "{\r\n    \"email\": \"{{jwtAdminEmail}}\"\r\n}\r\n"
                },
                {
                  "key": "secret",
                  "type": "string",
                  "value": "{{jwtSecret}}"
                },
                {
                  "key": "addTokenTo",
                  "type": "string",
                  "value": "header"
                },
                {
                  "key": "algorithm",
                  "type": "string",
                  "value": "HS256"
                },
                {
                  "key": "isSecretBase64Encoded",
                  "type": "boolean",
                  "value": false
                },
                {
                  "key": "headerPrefix",
                  "type": "string",
                  "value": "Bearer"
                },
                {
                  "key": "queryParamKey",
                  "type": "string",
                  "value": "token"
                },
                {
                  "key": "header",
                  "type": "string",
                  "value": "{}"
                }
              ],
              "type": "jwt"
            },
            "header": [],
            "method": "DELETE",
            "url": {
              "host": ["{{apiUrl}}users"],
              "path": ["{{jwtEmail}}"],
              "raw": "{{apiUrl}}users/{{jwtEmail}}"
            }
          },
          "response": []
        },
        {
          "name": "Get companies",
          "request": {
            "auth": {
              "jwt": [
                {
                  "key": "payload",
                  "type": "string",
                  "value": "{\r\n    \"email\": \"{{jwtEmail}}\"\r\n}\r\n"
                },
                {
                  "key": "secret",
                  "type": "string",
                  "value": "{{jwtSecret}}"
                },
                {
                  "key": "addTokenTo",
                  "type": "string",
                  "value": "header"
                },
                {
                  "key": "algorithm",
                  "type": "string",
                  "value": "HS256"
                },
                {
                  "key": "isSecretBase64Encoded",
                  "type": "boolean",
                  "value": false
                },
                {
                  "key": "headerPrefix",
                  "type": "string",
                  "value": "Bearer"
                },
                {
                  "key": "queryParamKey",
                  "type": "string",
                  "value": "token"
                },
                {
                  "key": "header",
                  "type": "string",
                  "value": "{}"
                }
              ],
              "type": "jwt"
            },
            "header": [],
            "method": "GET",
            "url": {
              "host": ["{{apiUrl}}users"],
              "path": ["{{jwtEmail}}", "companies"],
              "raw": "{{apiUrl}}users/{{jwtEmail}}/companies"
            }
          },
          "response": []
        },
        {
          "name": "Get companies / pagination",
          "request": {
            "auth": {
              "jwt": [
                {
                  "key": "payload",
                  "type": "string",
                  "value": "{\r\n    \"email\": \"{{jwtEmail}}\"\r\n}\r\n"
                },
                {
                  "key": "secret",
                  "type": "string",
                  "value": "{{jwtSecret}}"
                },
                {
                  "key": "addTokenTo",
                  "type": "string",
                  "value": "header"
                },
                {
                  "key": "algorithm",
                  "type": "string",
                  "value": "HS256"
                },
                {
                  "key": "isSecretBase64Encoded",
                  "type": "boolean",
                  "value": false
                },
                {
                  "key": "headerPrefix",
                  "type": "string",
                  "value": "Bearer"
                },
                {
                  "key": "queryParamKey",
                  "type": "string",
                  "value": "token"
                },
                {
                  "key": "header",
                  "type": "string",
                  "value": "{}"
                }
              ],
              "type": "jwt"
            },
            "header": [],
            "method": "GET",
            "url": {
              "host": ["{{apiUrl}}users"],
              "path": ["{{jwtEmail}}", "companies"],
              "query": [
                {
                  "key": "offset",
                  "value": "1"
                },
                {
                  "key": "limit",
                  "value": "2"
                }
              ],
              "raw": "{{apiUrl}}users/{{jwtEmail}}/companies?offset=1&limit=2"
            }
          },
          "response": []
        }
      ],
      "name": "Users"
    },
    {
      "item": [
        {
          "name": "Async reject",
          "request": {
            "auth": {
              "type": "noauth"
            },
            "header": [],
            "method": "GET",
            "url": {
              "host": ["{{apiUrl}}test"],
              "path": ["async-reject"],
              "raw": "{{apiUrl}}test/async-reject"
            }
          },
          "response": []
        },
        {
          "name": "Sync reject",
          "request": {
            "auth": {
              "type": "noauth"
            },
            "header": [],
            "method": "GET",
            "url": {
              "host": ["{{apiUrl}}test"],
              "path": ["sync-reject"],
              "raw": "{{apiUrl}}test/sync-reject"
            }
          },
          "response": []
        }
      ],
      "name": "Test"
    },
    {
      "name": "Index",
      "request": {
        "auth": {
          "type": "noauth"
        },
        "header": [],
        "method": "GET",
        "url": {
          "host": ["{{apiUrl}}"],
          "raw": "{{apiUrl}}"
        }
      },
      "response": []
    },
    {
      "name": "Not found",
      "request": {
        "auth": {
          "type": "noauth"
        },
        "header": [],
        "method": "GET",
        "url": {
          "host": ["{{apiUrl}}not-found-Xt2H"],
          "raw": "{{apiUrl}}not-found-Xt2H"
        }
      },
      "response": []
    }
  ]
}
