{
	"id": "d5cd2881-8c73-4493-aba8-8a01db496a16",
	"name": "Zero localhost",
	"values": [
		{
			"key": "apiUrl",
			"value": "http://localhost:3000/",
			"type": "default",
			"enabled": true
		},
		{
			"key": "existingCategoryName",
			"value": "E-commerce",
			"type": "default",
			"enabled": true
		},
		{
			"key": "exitingUserEmail",
			"value": "oliver.smith@example.com",
			"type": "default",
			"enabled": true
		},
		{
			"key": "jwtAdminEmail",
			"value": "admin@x.tyweuyag",
			"type": "default",
			"enabled": true
		},
		{
			"key": "jwtEmail",
			"value": "postman@x.tyweuyag",
			"type": "default",
			"enabled": true
		},
		{
			"key": "jwtSecret",
			"value": "Bw2GtzN2rCqG4AewJQr3",
			"type": "default",
			"enabled": true
		},
		{
			"key": "ids",
			"value": "",
			"type": "any",
			"enabled": true
		},
		{
			"key": "lastCategoryId",
			"value": "",
			"type": "any",
			"enabled": true
		},
		{
			"key": "lastCompanyId",
			"value": "",
			"type": "any",
			"enabled": true
		},
		{
			"key": "lastUserId",
			"value": "",
			"type": "any",
			"enabled": true
		},
		{
			"key": "nextCursor[0]",
			"value": "",
			"type": "any",
			"enabled": true
		},
		{
			"key": "nextCursor[1]",
			"value": "",
			"type": "any",
			"enabled": true
		}
	],
	"_postman_variable_scope": "environment",
	"_postman_exported_at": "2024-05-29T17:05:23.079Z",
	"_postman_exported_using": "Postman/11.1.14"
}